pyprote/__init__.py
pyprote/__main__.py
pyprote/cli_argument_defaults.py
pyprote/logging_config/logger_config.json
pyprote/logging_config/logger_config.py
pyprote/pyprote.py
pyprote/templates/.gitignore_template
pyprote/templates/Pipfile_template
pyprote/templates/README.md_template
pyprote/templates/package_name_template/__init__.py_template
pyprote/templates/package_name_template/__main__.py_template
pyprote/templates/package_name_template/logging_config_template/logger_config.json_template
pyprote/templates/package_name_template/logging_config_template/logger_config.py_template
pyprote/templates/package_name_template/package_name.py_template
pyprote/templates/pyproject.toml_template
pyprote/templates/pytest.ini_template
pyprote/templates/setup.cfg_template
pyprote/templates/tests_template/__init__.py_template
pyprote/templates/tests_template/conftest.py_template
pyprote/templates/tests_template/test_package_name.py_template
pyprote-2022.8.4.dist-info/entry_points.txt
pyprote-2022.8.4.dist-info/LICENSE
pyprote-2022.8.4.dist-info/WHEEL
pyprote-2022.8.4.dist-info/METADATA
pyprote-2022.8.4.dist-info/RECORD
