Metadata-Version: 2.1
Name: pyprote
Version: 2022.8.4
Summary: A tool for creating python packages.
Home-page: https://github.com/Cattes/pypote
License: LICENSE
Keywords: template,package,python
Author: Sebastian Cattes
Author-email: sebastian.cattes@inwt-statistics.de
Maintainer: Sebastian Cattes
Maintainer-email: sebastian.cattes@inwt-statistics.de
Requires-Python: >=3.10.0,<3.11
Classifier: Development Status :: 3 - Alpha
Classifier: Intended Audience :: Developers
Classifier: License :: Other/Proprietary License
Classifier: Operating System :: OS Independent
Classifier: Programming Language :: Python :: 3
Classifier: Programming Language :: Python :: 3.10
Classifier: Programming Language :: Python :: 3
Classifier: Programming Language :: Python :: 3 :: Only
Classifier: Programming Language :: Python :: 3.10
Project-URL: Documentation, https://github.com/Cattes/pypote
Project-URL: Repository, https://github.com/Cattes/pypote
